pybind11_mypy_demo.cpython-36m-i386-linux-gnu.so
pybind11_mypy_demo-0.0.1.dist-info/WHEEL
pybind11_mypy_demo-0.0.1.dist-info/METADATA
pybind11_mypy_demo-0.0.1.dist-info/top_level.txt
pybind11_mypy_demo-0.0.1.dist-info/RECORD
pybind11_mypy_demo-0.0.1.dist-info/LICENSE
